LICENSE.txt
MANIFEST.in
setup.cfg
setup.py
py2cytoscape/__init__.py
py2cytoscape.egg-info/PKG-INFO
py2cytoscape.egg-info/SOURCES.txt
py2cytoscape.egg-info/dependency_links.txt
py2cytoscape.egg-info/requires.txt
py2cytoscape.egg-info/top_level.txt
py2cytoscape/cyrest/__init__.py
py2cytoscape/cyrest/apply.py
py2cytoscape/cyrest/apps.py
py2cytoscape/cyrest/base.py
py2cytoscape/cyrest/collections.py
py2cytoscape/cyrest/command.py
py2cytoscape/cyrest/commands.py
py2cytoscape/cyrest/cybrowser.py
py2cytoscape/cyrest/cyndex2.py
py2cytoscape/cyrest/cyrest.py
py2cytoscape/cyrest/diffusion.py
py2cytoscape/cyrest/edge.py
py2cytoscape/cyrest/enrichmentmap.py
py2cytoscape/cyrest/group.py
py2cytoscape/cyrest/idmapper.py
py2cytoscape/cyrest/layout.py
py2cytoscape/cyrest/network.py
py2cytoscape/cyrest/networks.py
py2cytoscape/cyrest/node.py
py2cytoscape/cyrest/session.py
py2cytoscape/cyrest/styles.py
py2cytoscape/cyrest/table.py
py2cytoscape/cyrest/ui.py
py2cytoscape/cyrest/view.py
py2cytoscape/cyrest/vizmap.py
py2cytoscape/cytoscapejs/__init__.py
py2cytoscape/cytoscapejs/default_style.json
py2cytoscape/cytoscapejs/loader.js
py2cytoscape/cytoscapejs/template.html
py2cytoscape/cytoscapejs/viewer.py
py2cytoscape/data/__init__.py
py2cytoscape/data/algorithm_client.py
py2cytoscape/data/base_view.py
py2cytoscape/data/cynetwork.py
py2cytoscape/data/cyrest_client.py
py2cytoscape/data/edge_view.py
py2cytoscape/data/network_client.py
py2cytoscape/data/network_view.py
py2cytoscape/data/node_view.py
py2cytoscape/data/session_client.py
py2cytoscape/data/style.py
py2cytoscape/data/style_client.py
py2cytoscape/data/table.py
py2cytoscape/data/util_http.py
py2cytoscape/data/util_network.py
py2cytoscape/data/util_style.py
py2cytoscape/util/__init__.py
py2cytoscape/util/cytoscapejs.py
py2cytoscape/util/util_dataframe.py
py2cytoscape/util/util_graphlab.py
py2cytoscape/util/util_igraph.py
py2cytoscape/util/util_networkx.py
py2cytoscape/util/util_numpy.py