Metadata-Version: 1.1
Name: py2cytoscape
Version: 0.7.1
Summary: Utilities to use Cytoscape and Cytoscape.js from Python
Home-page: https://github.com/idekerlab/py2cytoscape
Author: Jorge Boucas
Author-email: jorge.boucas@age.mpg.de
License: MIT License
Keywords: data visualization,visualization,cytoscape,bioinformatics,graph,network
Platform: UNKNOWN
Classifier: Intended Audience :: Science/Research
Classifier: Intended Audience :: Developers
Classifier: Operating System :: OS Independent
Classifier: Development Status :: 3 - Alpha
Classifier: Programming Language :: Python :: 2.7
Classifier: Programming Language :: Python :: 3.4
Classifier: Programming Language :: Python :: 3.5
Classifier: License :: OSI Approved :: MIT License
Classifier: Topic :: Scientific/Engineering :: Bio-Informatics
Classifier: Topic :: Scientific/Engineering :: Information Analysis
Classifier: Topic :: Scientific/Engineering :: Mathematics
Classifier: Topic :: Scientific/Engineering :: Visualization
